digitalhub_runtime_python/__init__.py
digitalhub_runtime_python/entities/__init__.py
digitalhub_runtime_python/entities/_base/__init__.py
digitalhub_runtime_python/entities/_base/runtime_entity/__init__.py
digitalhub_runtime_python/entities/_base/runtime_entity/builder.py
digitalhub_runtime_python/entities/_commons/__init__.py
digitalhub_runtime_python/entities/_commons/enums.py
digitalhub_runtime_python/entities/function/__init__.py
digitalhub_runtime_python/entities/function/python/__init__.py
digitalhub_runtime_python/entities/function/python/builder.py
digitalhub_runtime_python/entities/function/python/entity.py
digitalhub_runtime_python/entities/function/python/models.py
digitalhub_runtime_python/entities/function/python/spec.py
digitalhub_runtime_python/entities/function/python/status.py
digitalhub_runtime_python/entities/function/python/utils.py
digitalhub_runtime_python/entities/run/__init__.py
digitalhub_runtime_python/entities/run/_base/__init__.py
digitalhub_runtime_python/entities/run/_base/builder.py
digitalhub_runtime_python/entities/run/_base/entity.py
digitalhub_runtime_python/entities/run/_base/spec.py
digitalhub_runtime_python/entities/run/_base/status.py
digitalhub_runtime_python/entities/run/_base/utils.py
digitalhub_runtime_python/entities/run/build/__init__.py
digitalhub_runtime_python/entities/run/build/builder.py
digitalhub_runtime_python/entities/run/build/entity.py
digitalhub_runtime_python/entities/run/build/spec.py
digitalhub_runtime_python/entities/run/build/status.py
digitalhub_runtime_python/entities/run/job/__init__.py
digitalhub_runtime_python/entities/run/job/builder.py
digitalhub_runtime_python/entities/run/job/entity.py
digitalhub_runtime_python/entities/run/job/spec.py
digitalhub_runtime_python/entities/run/job/status.py
digitalhub_runtime_python/entities/run/serve/__init__.py
digitalhub_runtime_python/entities/run/serve/builder.py
digitalhub_runtime_python/entities/run/serve/entity.py
digitalhub_runtime_python-0.14.0.dist-info/METADATA
digitalhub_runtime_python-0.14.0.dist-info/WHEEL
digitalhub_runtime_python-0.14.0.dist-info/licenses/AUTHORS
digitalhub_runtime_python-0.14.0.dist-info/licenses/LICENSE
digitalhub_runtime_python-0.14.0.dist-info/RECORD
